{
  "updatedAt": "2026-06-17T08:32:49.254Z",
  "piped": [
    {
      "url": "https://piped.video/api",
      "latency": 301
    },
    {
      "url": "https://api.piped.private.coffee",
      "latency": 758
    },
    {
      "url": "https://api.piped.projectsegfau.lt",
      "latency": 798
    }
  ],
  "invidious": [
    {
      "url": "https://yewtu.be",
      "latency": 861
    },
    {
      "url": "https://invidious.tiekoetter.com",
      "latency": 894
    }
  ],
  "cobalt": [],
  "stats": {
    "pipedTotal": 16,
    "pipedWorking": 3,
    "invidiousTotal": 21,
    "invidiousWorking": 2,
    "cobaltTotal": 4,
    "cobaltWorking": 0
  }
}